seatable_api/__init__.py
seatable_api/api_gateway.py
seatable_api/column.py
seatable_api/constants.py
seatable_api/context.py
seatable_api/convert_airtable.py
seatable_api/date_utils.py
seatable_api/exception.py
seatable_api/main.py
seatable_api/message.py
seatable_api/parsetab.py
seatable_api/query.py
seatable_api/socket_io.py
seatable_api/utils.py
tests/__init__.py
tests/dateutils_test.py
seatable_api_meta-0.0.1.dist-info/LICENSE
seatable_api_meta-0.0.1.dist-info/METADATA
seatable_api_meta-0.0.1.dist-info/WHEEL
seatable_api_meta-0.0.1.dist-info/top_level.txt
seatable_api_meta-0.0.1.dist-info/RECORD
