Metadata-Version: 2.1
Name: seatable-api-meta
Version: 0.0.1
Summary: Python client for SeaTable web api -- meta version
Home-page: https://github.com/seatable/seatable-api-python
Author: seatable
Author-email: support@seafile.com
License: Apache Licence
Platform: any
Classifier: Programming Language :: Python
Requires-Dist: requests
Requires-Dist: python-socketio (<5)
Requires-Dist: ply
Requires-Dist: python-dateutil
